schweizmobil_gpx/__init__.py
schweizmobil_gpx/downloader.py
schweizmobil_gpx-0.1.0.dist-info/licenses/LICENSE
schweizmobil_gpx-0.1.0.dist-info/METADATA
schweizmobil_gpx-0.1.0.dist-info/WHEEL
schweizmobil_gpx-0.1.0.dist-info/top_level.txt
schweizmobil_gpx-0.1.0.dist-info/RECORD
