Metadata-Version: 2.4
Name: schweizmobil_gpx
Version: 0.1.0
Summary: Package to download all your saved GPX tours from schweizmobil.ch
License: CC BY-SA 4.0
Classifier: Programming Language :: Python :: 3
Classifier: Operating System :: OS Independent
Classifier: Intended Audience :: End Users/Desktop
Requires-Python: >=3.7
License-File: LICENSE
Requires-Dist: requests
Dynamic: license-file
